jungle_chess/__init__.py
jungle_chess/__main__.py
jungle_chess/board.py
jungle_chess/constants.py
jungle_chess/game.py
jungle_chess/network.py
jungle_chess/piece.py
jungle_chess/version.py
jungle_chess/assets/fonts/MountainsofChristmas-Bold.ttf
jungle_chess/assets/fonts/Roboto-Bold.ttf
jungle_chess/assets/fonts/Roboto-Regular.ttf
jungle_chess/assets/fonts/aoyagireisyosimo2 Regular.ttf
jungle_chess/assets/images/1_green.png
jungle_chess/assets/images/1_red.png
jungle_chess/assets/images/2_green.png
jungle_chess/assets/images/2_red.png
jungle_chess/assets/images/3_green.png
jungle_chess/assets/images/3_red.png
jungle_chess/assets/images/4_green.png
jungle_chess/assets/images/4_red.png
jungle_chess/assets/images/5_green.png
jungle_chess/assets/images/5_red.png
jungle_chess/assets/images/6_green.png
jungle_chess/assets/images/6_red.png
jungle_chess/assets/images/7_green.png
jungle_chess/assets/images/7_red.png
jungle_chess/assets/images/8_green.png
jungle_chess/assets/images/8_red.png
jungle_chess/assets/images/arrow.svg
jungle_chess/assets/images/avatar_green.svg
jungle_chess/assets/images/avatar_green_d.svg
jungle_chess/assets/images/avatar_red.svg
jungle_chess/assets/images/avatar_red_d.svg
jungle_chess/assets/images/flag.svg
jungle_chess/assets/images/icon.png
jungle_chess/assets/images/menu_bg.jpg
jungle_chess/assets/images/piece_bg.png
jungle_chess/assets/images/table.png
jungle_chess/assets/sounds/Chinese New Year Is Coming.ogg
jungle_chess/assets/sounds/attack.ogg
jungle_chess/assets/sounds/bomb.ogg
jungle_chess/assets/sounds/fanfare-finish.ogg
jungle_chess/assets/sounds/finish.ogg
jungle_chess/assets/sounds/ready.ogg
jungle_chess/assets/sounds/slide.ogg
jungle_chess/assets/sounds/steps2.ogg
jungle_chess-1.0.0.dist-info/entry_points.txt
jungle_chess-1.0.0.dist-info/LICENSE
jungle_chess-1.0.0.dist-info/LICENSE-3RD-PARTY.md
jungle_chess-1.0.0.dist-info/WHEEL
jungle_chess-1.0.0.dist-info/METADATA
jungle_chess-1.0.0.dist-info/RECORD
