Metadata-Version: 2.1
Name: jungle-chess
Version: 1.0.0
Summary: Jungle Chess (Dou Shou Qi) is a network strategy game for two players.
Keywords: jungle chess,dou shou qi,animal chess,jungle game,game,pygame
Author-email: Sergei Kasaurov <sergei.kasaurov@gmail.com>
Requires-Python: >=3.8
Classifier: Development Status :: 5 - Production/Stable
Classifier: License :: OSI Approved :: MIT License
Classifier: Operating System :: OS Independent
Classifier: Programming Language :: Python :: 3 :: Only
Classifier: Programming Language :: Python :: 3.8
Classifier: Programming Language :: Python :: 3.9
Classifier: Programming Language :: Python :: 3.10
Classifier: Programming Language :: Python :: 3.11
Classifier: Programming Language :: Python :: 3.12
Classifier: Topic :: Games/Entertainment :: Board Games
Requires-Dist: pygame
Requires-Dist: pygame-menu
Project-URL: Changelog, https://github.com/barbanevosa/jungle-chess/blob/main/CHANGES.md
Project-URL: Homepage, https://github.com/barbanevosa/jungle-chess
Project-URL: Issues, https://github.com/barbanevosa/jungle-chess/issues
Project-URL: Repository, https://github.com/barbanevosa/jungle-chess.git
